odoo8_addon_stock_picking_deliver_uos-8.0.1.0.0.99.dev10-nspkg.pth
odoo_addons/stock_picking_deliver_uos/README.rst
odoo_addons/stock_picking_deliver_uos/__init__.py
odoo_addons/stock_picking_deliver_uos/__openerp__.py
odoo_addons/stock_picking_deliver_uos/i18n/de.po
odoo_addons/stock_picking_deliver_uos/i18n/es.po
odoo_addons/stock_picking_deliver_uos/i18n/eu.po
odoo_addons/stock_picking_deliver_uos/i18n/fr.po
odoo_addons/stock_picking_deliver_uos/i18n/it.po
odoo_addons/stock_picking_deliver_uos/i18n/sl.po
odoo_addons/stock_picking_deliver_uos/i18n/stock_picking_deliver_uos.pot
odoo_addons/stock_picking_deliver_uos/i18n/tr.po
odoo_addons/stock_picking_deliver_uos/static/description/icon.png
odoo_addons/stock_picking_deliver_uos/test/stock_partial_picking.yml
odoo_addons/stock_picking_deliver_uos/wizard/__init__.py
odoo_addons/stock_picking_deliver_uos/wizard/stock_transfer_details.py
odoo_addons/stock_picking_deliver_uos/wizard/stock_transfer_details_view.xml
odoo8_addon_stock_picking_deliver_uos-8.0.1.0.0.99.dev10.dist-info/METADATA
odoo8_addon_stock_picking_deliver_uos-8.0.1.0.0.99.dev10.dist-info/WHEEL
odoo8_addon_stock_picking_deliver_uos-8.0.1.0.0.99.dev10.dist-info/namespace_packages.txt
odoo8_addon_stock_picking_deliver_uos-8.0.1.0.0.99.dev10.dist-info/top_level.txt
odoo8_addon_stock_picking_deliver_uos-8.0.1.0.0.99.dev10.dist-info/RECORD
